{
  "band_name": "cuda_octant_850M",
  "dump_path": "results/4090-octant/cuda_octant_850M.bin",
  "tile_counts": {
    "total": 75130112,
    "normal": 75130112,
    "dead": 0,
    "overflow_poisoned": 0,
    "parse_errors": 0,
    "pct_dead": 0.0,
    "pct_poisoned": 0.0
  },
  "prime_count": {
    "count": 75130112,
    "min": 2052,
    "max": 2512,
    "mean": 2273.9415,
    "median": 2274.0,
    "std": 39.9025,
    "p95": 2340.0,
    "p99": 2367.0
  },
  "groups_per_tile": {
    "count": 75130112,
    "min": 1,
    "max": 24,
    "mean": 9.7571,
    "median": 10.0,
    "std": 2.6172,
    "p95": 14.0,
    "p99": 16.0,
    "histogram": [
      {
        "lo": 1.0,
        "hi": 3.3,
        "count": 352140
      },
      {
        "lo": 3.3,
        "hi": 5.6,
        "count": 3166420
      },
      {
        "lo": 5.6,
        "hi": 7.9,
        "count": 11310529
      },
      {
        "lo": 7.9,
        "hi": 10.2,
        "count": 31638698
      },
      {
        "lo": 10.2,
        "hi": 12.5,
        "count": 17519776
      },
      {
        "lo": 12.5,
        "hi": 14.8,
        "count": 8305659
      },
      {
        "lo": 14.8,
        "hi": 17.1,
        "count": 2685112
      },
      {
        "lo": 17.1,
        "hi": 19.4,
        "count": 140228
      },
      {
        "lo": 19.4,
        "hi": 21.7,
        "count": 11002
      },
      {
        "lo": 21.7,
        "hi": 24.0,
        "count": 548
      }
    ]
  },
  "ports_per_tile_total": {
    "count": 75130112,
    "min": 21,
    "max": 79,
    "mean": 51.1977,
    "median": 51.0,
    "std": 5.2654,
    "p95": 60.0,
    "p99": 63.0
  },
  "ports_per_face": {
    "O": {
      "count": 75130112,
      "min": 0,
      "max": 27,
      "mean": 12.7995,
      "median": 13.0,
      "std": 2.5846,
      "p95": 17.0,
      "p99": 19.0
    },
    "I": {
      "count": 75130112,
      "min": 0,
      "max": 27,
      "mean": 12.7998,
      "median": 13.0,
      "std": 2.5847,
      "p95": 17.0,
      "p99": 19.0
    },
    "L": {
      "count": 75130112,
      "min": 0,
      "max": 27,
      "mean": 12.7993,
      "median": 13.0,
      "std": 2.5845,
      "p95": 17.0,
      "p99": 19.0
    },
    "R": {
      "count": 75130112,
      "min": 0,
      "max": 28,
      "mean": 12.7991,
      "median": 13.0,
      "std": 2.5847,
      "p95": 17.0,
      "p99": 19.0
    }
  },
  "payload_budget": {
    "count": 75130112,
    "min": 29,
    "max": 123,
    "mean": 76.7961,
    "median": 77.0,
    "std": 8.2952,
    "p95": 90.0,
    "p99": 96.0,
    "budget": 125,
    "slack": {
      "count": 75130112,
      "min": 2,
      "max": 96,
      "mean": 48.2039,
      "median": 48.0,
      "std": 8.2952,
      "p95": 62.0,
      "p99": 68.0
    },
    "histogram_used": [
      {
        "lo": 29.0,
        "hi": 38.4,
        "count": 247
      },
      {
        "lo": 38.4,
        "hi": 47.8,
        "count": 18155
      },
      {
        "lo": 47.8,
        "hi": 57.2,
        "count": 768207
      },
      {
        "lo": 57.2,
        "hi": 66.6,
        "count": 7287752
      },
      {
        "lo": 66.6,
        "hi": 76.0,
        "count": 24706665
      },
      {
        "lo": 76.0,
        "hi": 85.4,
        "count": 31327514
      },
      {
        "lo": 85.4,
        "hi": 94.8,
        "count": 9836138
      },
      {
        "lo": 94.8,
        "hi": 104.2,
        "count": 1158357
      },
      {
        "lo": 104.2,
        "hi": 113.6,
        "count": 26815
      },
      {
        "lo": 113.6,
        "hi": 123.0,
        "count": 262
      }
    ]
  }
}